<?xml version="1.0" encoding="utf-8" ?>
<odoo>

    <record id="stock_picking_form_view_inherit" model="ir.ui.view">
        <field name="name">stock.picking.form.view.inherit</field>
        <field name="model">stock.picking</field>
        <field name="inherit_id" ref="stock.view_picking_form"/>
        <field name="arch" type="xml">

            <xpath expr="//field[@name='quantity_done']" position="before">
                <field name="is_operation_type" invisible="1"/>
                <field name="inventory_transfer_account_id" optional="hide"
                       attrs="{'column_invisible': [('parent.is_operation_type', '=', False)]}"/>

            </xpath>
            <xpath expr="//field[@name='origin']" position="after">
                <field name="is_operation_type" invisible="1"/>
                <field name="inventory_transfer_account_id" attrs="{'invisible': [('is_operation_type', '=', False)]}"/>
            </xpath>
        </field>
    </record>
</odoo>
